bagua_cuda116-0.9.2.dist-info/METADATA
bagua_cuda116-0.9.2.dist-info/LICENSE
bagua_cuda116-0.9.2.dist-info/WHEEL
bagua_cuda116-0.9.2.dist-info/top_level.txt
bagua_cuda116-0.9.2.dist-info/entry_points.txt
bagua_cuda116-0.9.2.dist-info/RECORD
bagua_cuda116.libs/libopen-pal-f100aaec.so.40.10.3
bagua_cuda116.libs/libz-4e3ca1c7.so.1.2.7
bagua_cuda116.libs/libhwloc-8a7ce5b6.so.5.7.5
bagua_cuda116.libs/libnuma-428e8baf.so.1.0.0
bagua_cuda116.libs/libopen-rte-22dd953b.so.40.10.3
bagua_cuda116.libs/libmpi-d86d2ca3.so.40.10.3
bagua_cuda116.libs/libltdl-35340011.so.7.3.0
bagua/bagua_define.py
bagua/__init__.py
bagua/version.py
bagua/service/__init__.py
bagua/service/autotune_service.py
bagua/service/autotune_system.py
bagua/service/autotune_task_manager.py
bagua/service/bayesian_optimizer.py
bagua/torch_api/bucket.py
bagua/torch_api/__init__.py
bagua/torch_api/utils.py
bagua/torch_api/tensor.py
bagua/torch_api/env.py
bagua/torch_api/communication.py
bagua/torch_api/distributed.py
bagua/torch_api/data_parallel/bagua_distributed.py
bagua/torch_api/data_parallel/__init__.py
bagua/torch_api/data_parallel/functional.py
bagua/torch_api/data_parallel/distributed.py
bagua/torch_api/model_parallel/__init__.py
bagua/torch_api/model_parallel/moe/__init__.py
bagua/torch_api/model_parallel/moe/utils.py
bagua/torch_api/model_parallel/moe/sharded_moe.py
bagua/torch_api/model_parallel/moe/layer.py
bagua/torch_api/model_parallel/moe/experts.py
bagua/torch_api/algorithms/q_adam.py
bagua/torch_api/algorithms/bytegrad.py
bagua/torch_api/algorithms/base.py
bagua/torch_api/algorithms/__init__.py
bagua/torch_api/algorithms/gradient_allreduce.py
bagua/torch_api/algorithms/async_model_average.py
bagua/torch_api/algorithms/decentralized.py
bagua/torch_api/checkpoint/__init__.py
bagua/torch_api/checkpoint/checkpointing.py
bagua/torch_api/contrib/__init__.py
bagua/torch_api/contrib/cached_dataset.py
bagua/torch_api/contrib/load_balancing_data_loader.py
bagua/torch_api/contrib/sync_batchnorm.py
bagua/torch_api/contrib/cache_loader.py
bagua/torch_api/contrib/utils/store.py
bagua/torch_api/contrib/utils/__init__.py
bagua/torch_api/contrib/utils/redis_store.py
