Metadata-Version: 2.1
Name: bagua-cuda116
Version: 0.9.2
Summary: Bagua is a deep learning training acceleration framework for PyTorch. It provides a one-stop training acceleration solution, including faster distributed training compared to PyTorch DDP, faster dataloader, kernel fusion, and more.
Home-page: https://github.com/BaguaSys/bagua
Author: Kuaishou AI Platform & DS3 Lab
Author-email: admin@mail.xrlian.com
Requires-Python: >=3.7
License-File: LICENSE
Requires-Dist: setuptools-rust
Requires-Dist: colorama
Requires-Dist: tqdm
Requires-Dist: deprecation (>=2.1)
Requires-Dist: pytest-benchmark (>=3.4)
Requires-Dist: scikit-optimize (>=0.8.1)
Requires-Dist: scikit-learn (!=1.0,<=1.0.1,>=0.24)
Requires-Dist: numpy
Requires-Dist: flask (>=2.0)
Requires-Dist: prometheus-client (>=0.11)
Requires-Dist: parallel-ssh (==2.9.1)
Requires-Dist: pydantic (>=1.8)
Requires-Dist: requests (>=2.25)
Requires-Dist: gorilla (==0.4.0)
Requires-Dist: gevent (>=21.8)
Requires-Dist: xxhash (>=2.0)
